[
    {
        "usi": 6942065469,
        "name": "Vivienne Labadie",
        "surname": "Becker",
        "birthDate": "42024",
        "gender": "Female",
        "gradeLevel": "Three",
        "raceEthnicity": "",
        "el20192020":"",
        "swdLevel":"",
        "monitoredEL20192020":"",
        "swdMonitored":"",
        "economicallyDisadvantaged":"",
        "atRisk":"",
        "newToUS":"",
        "accesForEll20192020":"",
        "leaCode":"123",
        "leaName":"My LEA",
        "schoolCode": "456",
        "schoolName": "My School",
        "fullAcademicYearStatus": "School",
        "mathAssesment": "PARCC",
        "mathAssesmentGradeSubject":3,
        "math3Plus":0,
        "continuouslyEnrolledDuringTestingWindow":"Yes",
        "mathOffGradeTest":"No",
        "elaOverallScaleScore":"567",
        "mathSummativeScoreStatus": "Valid Score",
        "registeredForRequiredMathAssessment": "Yes",
        "enrollmentAuditPopulation20192020": "Yes",
        "mathPerformanceLevel":1,
        "mathTestRepeater":"No",
        "ela3Plus":"",
        "osseApprovedELAMedicalExemption":"No",
        "osseApprovedAlternateAssessmentEligibility":"No",
        "elaParticipant":"Yes",
        "elaEligibleParticipant":"Yes",
        "ela4Plus":1,
        "elaPerformanceLevel":1,
        "math4Plus":0,
        "mathOverallScaleScore":675
    },
    {
        "usi": 6942065468,
        "name": "Hugh",
        "surname": "Whelan",
        "birthDate": "42024",
        "gender": "Female",
        "gradeLevel": "Three",
        "raceEthnicity": "",
        "el20192020":"",
        "swdLevel":"",
        "monitoredEL20192020":"",
        "swdMonitored":"",
        "economicallyDisadvantaged":"",
        "atRisk":"",
        "newToUS":"",
        "accesForEll20192020":"",
        "leaCode":"123",
        "leaName":"My LEA",
        "schoolCode": "456",
        "schoolName": "My School",
        "fullAcademicYearStatus": "School",
        "mathAssesment": "PARCC",
        "mathAssesmentGradeSubject":3,
        "math3Plus":0,
        "continuouslyEnrolledDuringTestingWindow":"Yes",
        "mathOffGradeTest":"No",
        "elaOverallScaleScore":"567",
        "mathSummativeScoreStatus": "Valid Score",
        "registeredForRequiredMathAssessment": "Yes",
        "enrollmentAuditPopulation20192020": "Yes",
        "mathPerformanceLevel":1,
        "mathTestRepeater":"No",
        "ela3Plus":"",
        "osseApprovedELAMedicalExemption":"No",
        "osseApprovedAlternateAssessmentEligibility":"No",
        "elaParticipant":"Yes",
        "elaEligibleParticipant":"Yes",
        "ela4Plus":1,
        "elaPerformanceLevel":1,
        "math4Plus":0,
        "mathOverallScaleScore":675
    } 
]